{"last_accessed": ["27 - 02-01-1970 - Syntax.txt", "26 - 02-01-1970 - Example Child Node Using a Node Pointer.txt", "17 - 02-01-1970 - Linking to outside resources.txt", "06 -  - Links and Pointers.txt", "48 - 02-01-1970 - Pointers.txt", "47 - 02-01-1970 - Pass Markers and Embedded Syntaxes.txt", "44 - 02-01-1970 - Dynamic Nodes.txt", "20 - 02-01-1970 - Urtext  Version- 0 4 0-alpha  Usage Guide and References.txt", "2a3.txt", "01 -  - Sublime Text Interface Tips.txt", "10 -  - project_settings.txt", "19 - 02-01-1970 - Linking to outside resources.txt", "51 - 02-01-1970 - Timezone List.txt", "36 - 02-01-1970 - Urtext Operations Guide.txt", "xdd.txt", "04 -  - Metadata.txt", "50 - 02-01-1970 - Collection - Timeline View.txt", "05 -  - Timestamps.txt", "oy5.txt", "25 - 02-01-1970 - This node is just here as a destination from the node pointer in  Urtext Syntax Guide.txt"], "project_settings": {"node_date_keyname": "", "id": ["00l", "00l", "00l", "00l", "00l", "00l", "00l", "00l", "00l", "00l", "00l", "00l", "00l", "00l", "00l", "00l"], "numerical_keys": ["_index", "index"], "google_calendar_id": null, "title": ["project_settings", "project_settings", "project_settings", "project_settings", "project_settings", "project_settings", "project_settings", "project_settings", "project_settings", "project_settings", "project_settings", "project_settings", "project_settings", "project_settings", "project_settings", "project_settings"], "case_sensitive": ["title", "notes", "comments", "project_title", "timezone", "timestamp_format", "filenames", "weblink", "timestamp"], "log_id": "", "strict": false, "timestamp": [], "console_log": true, "always_oneline_meta": false, "format_string": "$title\n-\n", "timezone": ["UTC"], "timestamp_format": ["%a., %b. %d, %Y, %I:%M %p", "%B %-d, %Y", "%B %Y", "%m-%d-%Y", "%a., %b. %d, %Y, %I:%M %p %z", "%a., %b. %d, %Y, %I:%M %p", "%A, %B %d, %Y, %I:%M %p", "%B %d, %Y, %I:%M %p", "%B %d, %Y, %I:%M%p", "%B %Y", "%Y", "%B %d, %Y", "%A, %B %d, %Y, %I:%M%p"], "preload": [], "google_auth_token": "token.json", "home": "a5m", "filenames": ["PREFIX", "DATE %m-%d-%Y", "TITLE"], "index": [100, 100, 100, 100, 100, 100, 100, 100, 100, 100, 100, 100, 100, 100, 100, 100]}, "path": "/Users/nathanielbeversluis/Library/Mobile Documents/iCloud~com~omz-software~Pythonista3/Documents/archive/docs", "title": "Urtext Documentation"}